LICENSE.rst
MANIFEST.in
README.md
setup.cfg
setup.py
bumpv/__init__.py
bumpv.egg-info/PKG-INFO
bumpv.egg-info/SOURCES.txt
bumpv.egg-info/dependency_links.txt
bumpv.egg-info/entry_points.txt
bumpv.egg-info/requires.txt
bumpv.egg-info/top_level.txt
bumpv/cli/__init__.py
bumpv/cli/cli.py
bumpv/client/__init__.py
bumpv/client/client.py
bumpv/client/exceptions.py
bumpv/client/config/__init__.py
bumpv/client/config/config.py
bumpv/client/config/exceptions.py
bumpv/client/files/__init__.py
bumpv/client/files/exceptions.py
bumpv/client/files/updater.py
bumpv/client/logging/__init__.py
bumpv/client/logging/logging.py
bumpv/client/vcs/__init__.py
bumpv/client/vcs/exceptions.py
bumpv/client/vcs/vcs.py
bumpv/client/versioning/__init__.py
bumpv/client/versioning/exceptions.py
bumpv/client/versioning/version.py
tests/test_cli_git.py
tests/test_cli_hg.py
tests/test_functions.py
tests/test_version_part.py