Metadata-Version: 2.1
Name: bumpv
Version: 0.8.0
Summary: Version-bump your software with a single command!
Home-page: https://github.com/kylieCat/bumpv
Author: Kylie Auld
Author-email: kylie.a@protonmail.com
License: MIT
Platform: UNKNOWN
Classifier: Development Status :: 4 - Beta
Classifier: Intended Audience :: Developers
Classifier: License :: OSI Approved :: MIT License
Classifier: Operating System :: OS Independent
Classifier: Programming Language :: Python
Classifier: Programming Language :: Python :: 3.6
Classifier: Programming Language :: Python :: Implementation :: PyPy
License-File: LICENSE.rst
